README.rst
setup.cfg
setup.py
eveparser/__init__.py
eveparser/exceptions.py
eveparser/utils.py
eveparser.egg-info/PKG-INFO
eveparser.egg-info/SOURCES.txt
eveparser.egg-info/dependency_links.txt
eveparser.egg-info/not-zip-safe
eveparser.egg-info/top_level.txt
eveparser/parsers/__init__.py
eveparser/parsers/assets.py
eveparser/parsers/cargo_scan.py
eveparser/parsers/chat.py
eveparser/parsers/contract.py
eveparser/parsers/dscan.py
eveparser/parsers/eft.py
eveparser/parsers/fitting.py
eveparser/parsers/industry.py
eveparser/parsers/killmail.py
eveparser/parsers/listing.py
eveparser/parsers/loot_history.py
eveparser/parsers/pi.py
eveparser/parsers/survey_scanner.py
eveparser/parsers/view_contents.py
eveparser/parsers/wallet.py