Metadata-Version: 1.1
Name: eveparser
Version: 0.10
Summary: A Python library to help parse various things that are copy/pastable from the Eve Online UI.
Home-page: https://github.com/Nothing4You/eveparser
Author: Richard Schwab
Author-email: richard@rep.pm
License: MIT
Platform: UNKNOWN
Classifier: Development Status :: 4 - Beta
Classifier: Environment :: Console
Classifier: Environment :: Web Environment
Classifier: Intended Audience :: Developers
Classifier: License :: OSI Approved :: MIT License
Classifier: Operating System :: MacOS :: MacOS X
Classifier: Operating System :: Microsoft :: Windows
Classifier: Operating System :: POSIX
Classifier: Programming Language :: Python
Classifier: Topic :: Games/Entertainment
Classifier: Programming Language :: Python :: 3.4
Classifier: Programming Language :: Python :: 3 :: Only
